asyncio_storage/__init__.py
asyncio_storage/base_storage.py
asyncio_storage/memory_storage.py
asyncio_storage/pickle_storage.py
asyncio_storage/redis_storage.py
ext/__init__.py
ext/aio/__init__.py
ext/aio/webhooks.py
ext/sync/__init__.py
ext/sync/webhooks.py
storage/__init__.py
storage/base_storage.py
storage/memory_storage.py
storage/pickle_storage.py
storage/redis_storage.py
artelebot-2.0.dist-info/LICENSE
artelebot-2.0.dist-info/METADATA
artelebot-2.0.dist-info/WHEEL
artelebot-2.0.dist-info/top_level.txt
artelebot-2.0.dist-info/RECORD
