Metadata-Version: 2.1
Name: artelebot
Version: 2.0
Summary: Arabic TeleBot
Home-page: 
Author: gay
Author-email: 
Project-URL: Bug Tracker, https://github.com/pypa/sampleproject/issues
Keywords: telebot,artelebot
Classifier: Development Status :: 1 - Planning
Classifier: Intended Audience :: Developers
Classifier: Programming Language :: Python :: 3
Classifier: Operating System :: Unix
Classifier: Operating System :: MacOS :: MacOS X
Classifier: Operating System :: Microsoft :: Windows
License-File: LICENSE
Requires-Dist: requests
